python_travis_docker_test/__init__.py
python_travis_docker_test/fibonacci.py
python_travis_docker_test-0.0.0.dist-info/DESCRIPTION.rst
python_travis_docker_test-0.0.0.dist-info/METADATA
python_travis_docker_test-0.0.0.dist-info/RECORD
python_travis_docker_test-0.0.0.dist-info/WHEEL
python_travis_docker_test-0.0.0.dist-info/metadata.json
python_travis_docker_test-0.0.0.dist-info/top_level.txt
