Metadata-Version: 2.0
Name: python-travis-docker-test
Version: 0.0.0
Summary: A sample Python project to demo travisCI Docker
Home-page: https://github.com/abrarsheikh/python_travis_docker_test
Author: The Python Packaging Authority
Author-email: pypa-dev@googlegroups.com
License: MIT
Keywords: python travisCI Docker
Platform: UNKNOWN
Classifier: Development Status :: 3 - Alpha
Classifier: Intended Audience :: Developers
Classifier: Topic :: Software Development :: Build Tools
Classifier: License :: OSI Approved :: MIT License
Classifier: Programming Language :: Python :: 2
Classifier: Programming Language :: Python :: 2.6
Classifier: Programming Language :: Python :: 2.7
Classifier: Programming Language :: Python :: 3
Classifier: Programming Language :: Python :: 3.3
Classifier: Programming Language :: Python :: 3.4
Classifier: Programming Language :: Python :: 3.5
